{
    "option.fs_updateUrl_limit.txt": {
        "global_cache": false,
        "version_id": 1000010,
        "version_string": "1.0.0 Alpha",
        "hash": "2eb3bf1141e73c5eb8fad06a42c5f2d4"
    },
    "option.fs_updateUrl_title_limit.txt": {
        "global_cache": false,
        "version_id": 1000010,
        "version_string": "1.0.0 Alpha",
        "hash": "dba2580697e730b173e3817616687e7c"
    },
    "option_explain.fs_updateUrl_title_limit.txt": {
        "global_cache": false,
        "version_id": 1000010,
        "version_string": "1.0.0 Alpha",
        "hash": "d41d8cd98f00b204e9800998ecf8427e"
    }
}